{"Identifier":"3fb0aa0c-ce04-4ee8-a51f-f392618b53f6","Created":"2018-05-31T00:00:00Z","Owner":{"FirstName":"3fb0aa0c-ce04-4ee8-a51f-f392618b53f6","LastName":"3fb0aa0c-ce04-4ee8-a51f-f392618b53f6","Site":{"Name":"Site 3fb0aa0c-ce04-4ee8-a51f-f392618b53f646ec32ab-7b1d-4042-a844-3ecb7bf52c7d","Identifier":"3fb0aa0c-ce04-4ee8-a51f-f392618b53f646ec32ab-7b1d-","Calendar":null,"NonWorkingSchedules":[],"Id":"09154912-e3e6-43b8-b135-a8f1010c0404","LastModified":"2018-05-31T00:00:00Z"},"Id":"46dada96-f077-4418-8d96-a8f1010c0404","LastModified":"2018-05-31T00:00:00Z"},"Employee":{"FirstName":"f7591d20-dd1d-4211-a890-7d1119aa889c","LastName":"Smith","PrimarySite":null,"Id":"60ad66dc-5313-44be-a2fc-a8f1010c0417","LastModified":"2018-05-31T00:15:00Z"},"Sla":null,"Timers":[{"Events":[{"CaseTimer":null,"CaseTimerSnapshot":{"CaseTimer":null,"SnapshotTime":"2018-05-31T00:05:00Z","OrdinalId":0,"IsDerived":false,"SnapshotData":{"SnapshotTime":"2018-05-31T00:05:00Z","Sla":null,"CaseTimer":{"Name":"Case Timer Template Name 15299e49-bb3e-4bfd-8749-baeb562a4f0b","RespectNonWorkingSchedule":true,"RespectWorkCalendar":true,"RespectSlaClock":true,"DisplayOnCase":true,"CaseTimerType":"CaseTimer","NonWorkingEventSource":"EmployeesPrimarySite","Started":"2018-05-31T00:05:00Z","Stopped":null,"IsActive":true,"RunTime":"00:00:00","Offset":"00:00:00","ElapsedTime":"00:00:00","LastCalculated":null,"ErrorTime":null,"CurrentNonWorkingTimePeriodTypes":"None","LastNonWorkingTimePeriodTypes":"None","CurrentEffectiveClockState":"RunningAndAccruingTime","Case":{"Identifier":"3fb0aa0c-ce04-4ee8-a51f-f392618b53f6","Owner":{"FirstName":"3fb0aa0c-ce04-4ee8-a51f-f392618b53f6","LastName":"3fb0aa0c-ce04-4ee8-a51f-f392618b53f6","Site":{"Name":"Site 3fb0aa0c-ce04-4ee8-a51f-f392618b53f646ec32ab-7b1d-4042-a844-3ecb7bf52c7d","Identifier":"3fb0aa0c-ce04-4ee8-a51f-f392618b53f646ec32ab-7b1d-","Calendar":null,"NonWorkingSchedules":[],"Id":"09154912-e3e6-43b8-b135-a8f1010c0404","LastModified":"2018-05-31T00:00:00Z"},"Id":"46dada96-f077-4418-8d96-a8f1010c0404","LastModified":"2018-05-31T00:00:00Z"},"Employee":{"FirstName":"16d8a6ea-c05a-40a1-9709-96bf2e722c5a","LastName":"Smith","PrimarySite":null,"Id":"cf8add15-a1de-477f-9ad3-a8f1010c0415","LastModified":"2018-05-31T00:00:00Z"},"Id":"26c0a524-d02e-45dd-9af3-a8f1010c0404","LastModified":"2018-05-31T00:05:00Z"},"Id":"2f427dd9-7b77-495c-b0df-a8f1010c0427","LastModified":null},"NonWorkingTimePeriodsFromCase":[]},"UniqueId":"6e37822a-c7fa-4490-95b7-094513516718","Id":"a01a413a-bb42-4059-8166-a8f1010c042b","LastModified":"2018-05-31T00:05:00Z"},"EventData":{"TemporalEventArgs":null,"CalculationLogEventArgs":{"CalculationLogId":"00000000-0000-0000-0000-000000000000","SlaId":"00000000-0000-0000-0000-000000000000","SlaControlPoint":null},"UserEventArgs":null,"DataChangedEventArgs":null},"IsInherited":false,"AppIdentifier":"agent","EventIdentifierString":"CalculationLog:CaseTimerAdded","EventIdentifier":{"Key":"CalculationLog:CaseTimerAdded","IsDerivedEvent":false,"IsUserEvent":false,"IsCalculationLogEvent":true,"IsCaseTimerCreationEvent":true,"IsSlaBreachEvent":false,"IsTemporalEvent":false,"IsDataChangeEvent":false,"IsMiscellaneousEvent":false},"IsCaseTimerCreationEvent":true,"EventType":"CalculationLog","EventTime":"2018-05-31T00:05:00Z","OrdinalId":0,"IsDerived":false,"Id":"af2f49d5-0b92-4e4a-9b54-a8f1010c042b","LastModified":"2018-05-31T00:05:00Z"},{"CaseTimer":null,"CaseTimerSnapshot":{"CaseTimer":null,"SnapshotTime":"2018-05-31T00:05:00.0000001Z","OrdinalId":0,"IsDerived":true,"SnapshotData":{"SnapshotTime":"2018-05-31T00:05:00.0000001Z","Sla":null,"CaseTimer":{"Name":"Case Timer Template Name 15299e49-bb3e-4bfd-8749-baeb562a4f0b","RespectNonWorkingSchedule":true,"RespectWorkCalendar":true,"RespectSlaClock":true,"DisplayOnCase":true,"CaseTimerType":"CaseTimer","NonWorkingEventSource":"EmployeesPrimarySite","Started":"2018-05-31T00:05:00Z","Stopped":null,"IsActive":true,"RunTime":"00:00:00","Offset":"00:00:00","ElapsedTime":"00:00:00","LastCalculated":null,"ErrorTime":null,"CurrentNonWorkingTimePeriodTypes":"None","LastNonWorkingTimePeriodTypes":"None","CurrentEffectiveClockState":"RunningAndAccruingTime","Case":{"Identifier":"3fb0aa0c-ce04-4ee8-a51f-f392618b53f6","Owner":{"FirstName":"3fb0aa0c-ce04-4ee8-a51f-f392618b53f6","LastName":"3fb0aa0c-ce04-4ee8-a51f-f392618b53f6","Site":{"Name":"Site 3fb0aa0c-ce04-4ee8-a51f-f392618b53f646ec32ab-7b1d-4042-a844-3ecb7bf52c7d","Identifier":"3fb0aa0c-ce04-4ee8-a51f-f392618b53f646ec32ab-7b1d-","Calendar":null,"NonWorkingSchedules":[],"Id":"09154912-e3e6-43b8-b135-a8f1010c0404","LastModified":"2018-05-31T00:00:00Z"},"Id":"46dada96-f077-4418-8d96-a8f1010c0404","LastModified":"2018-05-31T00:00:00Z"},"Employee":{"FirstName":"16d8a6ea-c05a-40a1-9709-96bf2e722c5a","LastName":"Smith","PrimarySite":null,"Id":"cf8add15-a1de-477f-9ad3-a8f1010c0415","LastModified":"2018-05-31T00:00:00Z"},"Id":"26c0a524-d02e-45dd-9af3-a8f1010c0404","LastModified":"2018-05-31T00:05:00Z"},"Id":"2f427dd9-7b77-495c-b0df-a8f1010c0427","LastModified":null},"NonWorkingTimePeriodsFromCase":[]},"UniqueId":"c4a54984-43d7-4fb8-8003-3abf93858a18","Id":"3243c703-675c-4b73-8326-a8f1010c042b","LastModified":"2018-05-31T00:05:00Z"},"EventData":{"TemporalEventArgs":null,"CalculationLogEventArgs":null,"UserEventArgs":null,"DataChangedEventArgs":null},"IsInherited":false,"AppIdentifier":"agent","EventIdentifierString":"Derived:TimerStartedAccruingTime","EventIdentifier":{"Key":"Derived:TimerStartedAccruingTime","IsDerivedEvent":true,"IsUserEvent":false,"IsCalculationLogEvent":false,"IsCaseTimerCreationEvent":false,"IsSlaBreachEvent":false,"IsTemporalEvent":false,"IsDataChangeEvent":false,"IsMiscellaneousEvent":false},"IsCaseTimerCreationEvent":false,"EventType":"Derived","EventTime":"2018-05-31T00:05:00Z","OrdinalId":0,"IsDerived":true,"Id":"747b6396-dcff-4dc5-b9a0-a8f1010c042b","LastModified":"2018-05-31T00:05:00Z"},{"CaseTimer":null,"CaseTimerSnapshot":{"CaseTimer":null,"SnapshotTime":"2018-05-31T00:20:00Z","OrdinalId":0,"IsDerived":false,"SnapshotData":{"SnapshotTime":"2018-05-31T00:20:00Z","Sla":null,"CaseTimer":{"Name":"Case Timer Template Name 15299e49-bb3e-4bfd-8749-baeb562a4f0b","RespectNonWorkingSchedule":true,"RespectWorkCalendar":true,"RespectSlaClock":true,"DisplayOnCase":true,"CaseTimerType":"CaseTimer","NonWorkingEventSource":"EmployeesPrimarySite","Started":"2018-05-31T00:05:00Z","Stopped":null,"IsActive":true,"RunTime":"00:05:00","Offset":"00:00:00","ElapsedTime":"00:05:00","LastCalculated":"2018-05-31T00:10:00Z","ErrorTime":null,"CurrentNonWorkingTimePeriodTypes":"None","LastNonWorkingTimePeriodTypes":"None","CurrentEffectiveClockState":"RunningAndAccruingTime","Case":{"Identifier":"3fb0aa0c-ce04-4ee8-a51f-f392618b53f6","Owner":{"FirstName":"3fb0aa0c-ce04-4ee8-a51f-f392618b53f6","LastName":"3fb0aa0c-ce04-4ee8-a51f-f392618b53f6","Site":{"Name":"Site 3fb0aa0c-ce04-4ee8-a51f-f392618b53f646ec32ab-7b1d-4042-a844-3ecb7bf52c7d","Identifier":"3fb0aa0c-ce04-4ee8-a51f-f392618b53f646ec32ab-7b1d-","Calendar":null,"NonWorkingSchedules":[],"Id":"09154912-e3e6-43b8-b135-a8f1010c0404","LastModified":"2018-05-31T00:00:00Z"},"Id":"46dada96-f077-4418-8d96-a8f1010c0404","LastModified":"2018-05-31T00:00:00Z"},"Employee":{"FirstName":"f7591d20-dd1d-4211-a890-7d1119aa889c","LastName":"Smith","PrimarySite":null,"Id":"60ad66dc-5313-44be-a2fc-a8f1010c0417","LastModified":"2018-05-31T00:15:00Z"},"Id":"26c0a524-d02e-45dd-9af3-a8f1010c0404","LastModified":"2018-05-31T00:15:00Z"},"Id":"2f427dd9-7b77-495c-b0df-a8f1010c0427","LastModified":"2018-05-31T00:10:00Z"},"NonWorkingTimePeriodsFromCase":[]},"UniqueId":"89d78156-1384-4340-8b4a-1659dbf8ef7f","Id":"8baa5ff6-1021-4008-bfad-a8f1010c0461","LastModified":"2018-05-31T00:20:00Z"},"EventData":{"TemporalEventArgs":null,"CalculationLogEventArgs":null,"UserEventArgs":null,"DataChangedEventArgs":{"ChangeType":3,"PropertyPath":"CaseTimer.Case.Employee","PriorValue":{"FirstName":"16d8a6ea-c05a-40a1-9709-96bf2e722c5a","LastName":"Smith","PrimarySite":null,"Id":"cf8add15-a1de-477f-9ad3-a8f1010c0415","LastModified":"2018-05-31T00:00:00Z"},"NewValue":{"FirstName":"f7591d20-dd1d-4211-a890-7d1119aa889c","LastName":"Smith","PrimarySite":null,"Id":"60ad66dc-5313-44be-a2fc-a8f1010c0417","LastModified":"2018-05-31T00:15:00Z"}}},"IsInherited":false,"AppIdentifier":"agent","EventIdentifierString":"DataChange:Case.Employee","EventIdentifier":{"Key":"DataChange:Case.Employee","IsDerivedEvent":false,"IsUserEvent":false,"IsCalculationLogEvent":false,"IsCaseTimerCreationEvent":false,"IsSlaBreachEvent":false,"IsTemporalEvent":false,"IsDataChangeEvent":true,"IsMiscellaneousEvent":false},"IsCaseTimerCreationEvent":false,"EventType":"DataChange","EventTime":"2018-05-31T00:15:00Z","OrdinalId":0,"IsDerived":false,"Id":"4da8da23-1077-47b7-89e6-a8f1010c0461","LastModified":"2018-05-31T00:20:00Z"}],"Name":"Case Timer Template Name 15299e49-bb3e-4bfd-8749-baeb562a4f0b","RespectNonWorkingSchedule":true,"RespectWorkCalendar":true,"RespectSlaClock":true,"DisplayOnCase":true,"CaseTimerType":"CaseTimer","NonWorkingEventSource":"EmployeesPrimarySite","Started":"2018-05-31T00:05:00Z","Stopped":null,"IsActive":true,"RunTime":"00:15:00","Offset":"00:00:00","ElapsedTime":"00:15:00","LastCalculated":"2018-05-31T00:20:00Z","ErrorTime":null,"CurrentNonWorkingTimePeriodTypes":"None","LastNonWorkingTimePeriodTypes":"None","CurrentEffectiveClockState":"RunningAndAccruingTime","Case":null,"Id":"2f427dd9-7b77-495c-b0df-a8f1010c0427","LastModified":"2018-05-31T00:20:00Z"}],"Id":"26c0a524-d02e-45dd-9af3-a8f1010c0404","LastModified":"2018-05-31T00:15:00Z"}